[
  {
    "id": "/service/board/jirum/19221230?od=T31&po=0&category=0&groupCd=",
    "site": "clien",
    "title": "에이서 스위프트 GO 16 AI SFG16-74-7412 루나 U7-258V IPS 32G 1T Win11 노트북 156만",
    "url": "https://www.clien.net/service/board/jirum/19221230?od=T31&po=0&category=0&groupCd=",
    "thumb": "https://edgio.clien.net/F01/2026/7/15768974/1a0449d1f62c73.png?scale=width:480",
    "score": 193000,
    "views": 193000,
    "crawled_at": "2026-07-13T15:42:50.991996+00:00"
  },
  {
    "id": "/service/board/jirum/19220911?od=T31&po=0&category=0&groupCd=",
    "site": "clien",
    "title": "[iOS] Remote, Mouse & Keyboard 평생 IAP 일시 무료",
    "url": "https://www.clien.net/service/board/jirum/19220911?od=T31&po=0&category=0&groupCd=",
    "thumb": "https://edgio.clien.net/F01/2026/7/15768519/139d7db1884d2b.jpeg?scale=width:480",
    "score": 191000,
    "views": 191000,
    "crawled_at": "2026-07-13T15:42:50.991996+00:00"
  },
  {
    "id": "/service/board/jirum/19221739?od=T31&po=0&category=0&groupCd=",
    "site": "clien",
    "title": "온누리상품권 계란 할인",
    "url": "https://www.clien.net/service/board/jirum/19221739?od=T31&po=0&category=0&groupCd=",
    "thumb": "https://edgio.clien.net/F01/2026/7/15769640/3110b020713f95.png?scale=width:480",
    "score": 166000,
    "views": 166000,
    "crawled_at": "2026-07-13T15:42:50.991996+00:00"
  },
  {
    "id": "/service/board/jirum/19221208?od=T31&po=0&category=0&groupCd=",
    "site": "clien",
    "title": "TCL 55Q9B 4K QD-Mini LED 스마트 TV 139cm(55인치) 기사방문설치",
    "url": "https://www.clien.net/service/board/jirum/19221208?od=T31&po=0&category=0&groupCd=",
    "thumb": "https://edgio.clien.net/F01/2026/7/15768937/172161e64976f2.png?scale=width:480",
    "score": 162000,
    "views": 162000,
    "crawled_at": "2026-07-13T15:42:50.991996+00:00"
  },
  {
    "id": "/service/board/jirum/19221868?od=T31&po=0&category=0&groupCd=",
    "site": "clien",
    "title": "[iOS] Cove: 집중, 방해 앱 차단, 디지털 디톡스 리딤",
    "url": "https://www.clien.net/service/board/jirum/19221868?od=T31&po=0&category=0&groupCd=",
    "thumb": "https://edgio.clien.net/F01/2026/7/15769759/1433d167c36447.jpeg?scale=width:480",
    "score": 160000,
    "views": 160000,
    "crawled_at": "2026-07-13T15:42:50.991996+00:00"
  },
  {
    "id": "/service/board/jirum/19220885?od=T31&po=0&category=0&groupCd=",
    "site": "clien",
    "title": "[옥션] 맥심 카누 더블샷라떼 50t 2개 (33,240원/무료)",
    "url": "https://www.clien.net/service/board/jirum/19220885?od=T31&po=0&category=0&groupCd=",
    "thumb": "https://edgio.clien.net/F01/2026/7/15768469/16d81c0e91809a.jpg?scale=width:480",
    "score": 157000,
    "views": 157000,
    "crawled_at": "2026-07-13T15:42:50.991996+00:00"
  },
  {
    "id": "/service/board/jirum/19221077?od=T31&po=0&category=0&groupCd=",
    "site": "clien",
    "title": "[WearOS] SamWatch Analog Phi 2 2025 일시 무료",
    "url": "https://www.clien.net/service/board/jirum/19221077?od=T31&po=0&category=0&groupCd=",
    "thumb": "https://edgio.clien.net/F01/2026/7/15768767/19efa2918585a3.png?scale=width:480",
    "score": 144000,
    "views": 144000,
    "crawled_at": "2026-07-13T15:42:50.991996+00:00"
  },
  {
    "id": "/service/board/jirum/19220883?od=T31&po=0&category=0&groupCd=",
    "site": "clien",
    "title": "[G마켓] 건국 고칼슘두유 190ml 72팩 (23,500원/무배) 9",
    "url": "https://www.clien.net/service/board/jirum/19220883?od=T31&po=0&category=0&groupCd=",
    "thumb": "https://edgio.clien.net/F01/2026/7/15768468/19b8ec04a86aad.jpg?scale=width:480",
    "score": 140000,
    "views": 140000,
    "crawled_at": "2026-07-13T15:42:50.991996+00:00"
  },
  {
    "id": "/service/board/jirum/19222506?od=T31&po=0&category=0&groupCd=",
    "site": "clien",
    "title": "[WearOS] Pace PRO: Watch face 외 일시 무료",
    "url": "https://www.clien.net/service/board/jirum/19222506?od=T31&po=0&category=0&groupCd=",
    "thumb": "https://edgio.clien.net/F01/2026/7/15770555/14818c700ebde7.jpeg?scale=width:480",
    "score": 132000,
    "views": 132000,
    "crawled_at": "2026-07-13T15:42:50.991996+00:00"
  },
  {
    "id": "/service/board/jirum/19223573?od=T31&po=0&category=0&groupCd=",
    "site": "clien",
    "title": "[iOS/Android] Towaga: Among Shadows 무료",
    "url": "https://www.clien.net/service/board/jirum/19223573?od=T31&po=0&category=0&groupCd=",
    "thumb": "https://edgio.clien.net/F01/2026/7/15771848/1b2a385d44448c.jpeg?scale=width:480",
    "score": 128000,
    "views": 128000,
    "crawled_at": "2026-07-13T15:42:50.991996+00:00"
  },
  {
    "id": "/service/board/jirum/19224109?od=T31&po=0&category=0&groupCd=",
    "site": "clien",
    "title": "(에픽 게임즈) Tattoo Tycoon 무료 (7월17일 00시까지)",
    "url": "https://www.clien.net/service/board/jirum/19224109?od=T31&po=0&category=0&groupCd=",
    "thumb": "https://edgio.clien.net/F01/2026/7/15772558/1536eee910a754.png?scale=width:480",
    "score": 126000,
    "views": 126000,
    "crawled_at": "2026-07-13T15:42:50.991996+00:00"
  },
  {
    "id": "/service/board/jirum/19223888?od=T31&po=0&category=0&groupCd=",
    "site": "clien",
    "title": "[iOS] Orbital Focus 집중 로켓 타이머 일시 무료",
    "url": "https://www.clien.net/service/board/jirum/19223888?od=T31&po=0&category=0&groupCd=",
    "thumb": "https://edgio.clien.net/F01/2026/7/15772248/151f802d9c023b.jpeg?scale=width:480",
    "score": 122000,
    "views": 122000,
    "crawled_at": "2026-07-13T15:42:50.991996+00:00"
  },
  {
    "id": "/service/board/jirum/19222263?od=T31&po=0&category=0&groupCd=",
    "site": "clien",
    "title": "(인덕션x)셰프리아 아르노 클래식 프라이팬 28cm 8,900원",
    "url": "https://www.clien.net/service/board/jirum/19222263?od=T31&po=0&category=0&groupCd=",
    "thumb": "https://edgio.clien.net/F01/2026/7/15770243/146c441df1846d.jpg?scale=width:480",
    "score": 122000,
    "views": 122000,
    "crawled_at": "2026-07-13T15:42:50.991996+00:00"
  },
  {
    "id": "/service/board/jirum/19223017?od=T31&po=0&category=0&groupCd=",
    "site": "clien",
    "title": "[WearOS] SamWatch S Delta S FIT 2 2024 일시 무료",
    "url": "https://www.clien.net/service/board/jirum/19223017?od=T31&po=0&category=0&groupCd=",
    "thumb": "https://edgio.clien.net/F01/2026/7/15771179/1806905e10d512.png?scale=width:480",
    "score": 112000,
    "views": 112000,
    "crawled_at": "2026-07-13T15:42:50.991996+00:00"
  },
  {
    "id": "/service/board/jirum/19221696?od=T31&po=0&category=0&groupCd=",
    "site": "clien",
    "title": "[W컨셉] 하겐다즈 파인트 5개 (38,500원)",
    "url": "https://www.clien.net/service/board/jirum/19221696?od=T31&po=0&category=0&groupCd=",
    "thumb": "https://edgio.clien.net/F01/2026/7/15769562/1761fa333466ab.jpeg?scale=width:480",
    "score": 112000,
    "views": 112000,
    "crawled_at": "2026-07-13T15:42:50.991996+00:00"
  },
  {
    "id": "/service/board/jirum/19224887?od=T31&po=0&category=0&groupCd=",
    "site": "clien",
    "title": "[iOS/Android] 베어너클 4(Streets of Rage 4) (3,300원)",
    "url": "https://www.clien.net/service/board/jirum/19224887?od=T31&po=0&category=0&groupCd=",
    "thumb": "https://edgio.clien.net/F01/2026/7/15773551/15ab0ca32ec568.webp?scale=width:480",
    "score": 108000,
    "views": 108000,
    "crawled_at": "2026-07-13T15:42:50.991996+00:00"
  },
  {
    "id": "19224294",
    "site": "clien",
    "title": "[알리익스프레스] 여름아 반가워 정보 안내 (클리앙 전용 할인코드,결제할인)",
    "url": "https://www.clien.net/service/board/jirum/19224294",
    "thumb": "https://edgio.clien.net/F01/2026/7/15772792/1b79bf835a3ddb.png?scale=width:480",
    "score": 102000,
    "views": 102000,
    "crawled_at": "2026-07-13T15:42:50.991996+00:00"
  },
  {
    "id": "/service/board/jirum/19224294?od=T31&po=0&category=0&groupCd=",
    "site": "clien",
    "title": "[알리익스프레스] 여름아 반가워 정보 안내 (클리앙 전용 할인코드,결제할인)",
    "url": "https://www.clien.net/service/board/jirum/19224294?od=T31&po=0&category=0&groupCd=",
    "thumb": "https://edgio.clien.net/F01/2026/7/15772792/1b79bf835a3ddb.png?scale=width:480",
    "score": 102000,
    "views": 102000,
    "crawled_at": "2026-07-13T15:42:50.991996+00:00"
  },
  {
    "id": "/service/board/jirum/19224099?od=T31&po=0&category=0&groupCd=",
    "site": "clien",
    "title": "(에픽 게임즈) 열혈경파 쿠니오군 외전: River City Girls 2 무료 (7월10 00시까지, 해",
    "url": "https://www.clien.net/service/board/jirum/19224099?od=T31&po=0&category=0&groupCd=",
    "thumb": "https://edgio.clien.net/F01/2026/7/15772554/1874c6034231d9.png?scale=width:480",
    "score": 101000,
    "views": 101000,
    "crawled_at": "2026-07-13T15:42:50.991996+00:00"
  },
  {
    "id": "/service/board/jirum/19223634?od=T31&po=0&category=0&groupCd=",
    "site": "clien",
    "title": "[네이버] ASUS TUF P1 마우스 패드 (3,900원)",
    "url": "https://www.clien.net/service/board/jirum/19223634?od=T31&po=0&category=0&groupCd=",
    "thumb": "https://edgio.clien.net/F01/2026/7/15771905/1b2e2ecd876fbb.jpeg?scale=width:480",
    "score": 101000,
    "views": 101000,
    "crawled_at": "2026-07-13T15:42:50.991996+00:00"
  },
  {
    "id": "/service/board/jirum/19223864?od=T31&po=0&category=0&groupCd=",
    "site": "clien",
    "title": "[WearOS] HMK WD185 일시 무료",
    "url": "https://www.clien.net/service/board/jirum/19223864?od=T31&po=0&category=0&groupCd=",
    "thumb": "https://edgio.clien.net/F01/2026/7/15772202/32075fdc5aca37.jpeg?scale=width:480",
    "score": 9737,
    "views": 9737,
    "crawled_at": "2026-07-13T15:42:50.991996+00:00"
  },
  {
    "id": "/service/board/jirum/19223444?od=T31&po=0&category=0&groupCd=",
    "site": "clien",
    "title": "[WearOS] HMKWatch Digital 163 K 일시 무료",
    "url": "https://www.clien.net/service/board/jirum/19223444?od=T31&po=0&category=0&groupCd=",
    "thumb": "https://edgio.clien.net/F01/2026/7/15771707/1b1616ab6f7506.jpeg?scale=width:480",
    "score": 9341,
    "views": 9341,
    "crawled_at": "2026-07-13T15:42:50.991996+00:00"
  },
  {
    "id": "/service/board/jirum/19221087?od=T31&po=0&category=0&groupCd=",
    "site": "clien",
    "title": "[네이버] 양파 중사이즈 3kg (460원)",
    "url": "https://www.clien.net/service/board/jirum/19221087?od=T31&po=0&category=0&groupCd=",
    "thumb": "https://edgio.clien.net/F01/2026/7/15768792/30bcea4979cdab.jpeg?scale=width:480",
    "score": 9073,
    "views": 9073,
    "crawled_at": "2026-07-13T15:42:50.991996+00:00"
  },
  {
    "id": "/service/board/jirum/19225309?od=T31&po=0&category=0&groupCd=",
    "site": "clien",
    "title": "[iOS] Sudoku 스도쿠 숫자 퍼즐 논리 일시 무료",
    "url": "https://www.clien.net/service/board/jirum/19225309?od=T31&po=0&category=0&groupCd=",
    "thumb": "https://edgio.clien.net/F01/2026/7/15774238/1c1084a02d8366.jpeg?scale=width:480",
    "score": 8179,
    "views": 8179,
    "crawled_at": "2026-07-13T15:42:50.991996+00:00"
  },
  {
    "id": "/service/board/jirum/19222902?od=T31&po=0&category=0&groupCd=",
    "site": "clien",
    "title": "[네이버] 랄츠비 프로바이오틱스10포 (0원)",
    "url": "https://www.clien.net/service/board/jirum/19222902?od=T31&po=0&category=0&groupCd=",
    "thumb": "https://edgio.clien.net/F01/2026/7/15771081/31a8f1f44b6ac9.jpeg?scale=width:480",
    "score": 7313,
    "views": 7313,
    "crawled_at": "2026-07-13T15:42:50.991996+00:00"
  },
  {
    "id": "/service/board/jirum/19225082?od=T31&po=0&category=0&groupCd=",
    "site": "clien",
    "title": "[WatchOS] Poly Strike: Watch Space Game 일시 무료",
    "url": "https://www.clien.net/service/board/jirum/19225082?od=T31&po=0&category=0&groupCd=",
    "thumb": "https://edgio.clien.net/F01/2026/7/15773837/15bd3d75e74789.jpeg?scale=width:480",
    "score": 7059,
    "views": 7059,
    "crawled_at": "2026-07-13T15:42:50.991996+00:00"
  },
  {
    "id": "/service/board/jirum/19224886?od=T31&po=0&category=0&groupCd=",
    "site": "clien",
    "title": "[WearOS] Fasttrack Realistic PDX WF외 일시 무료",
    "url": "https://www.clien.net/service/board/jirum/19224886?od=T31&po=0&category=0&groupCd=",
    "thumb": "https://edgio.clien.net/F01/2026/7/15773548/18e9e181cb4c4c.jpeg?scale=width:480",
    "score": 6858,
    "views": 6858,
    "crawled_at": "2026-07-13T15:42:50.991996+00:00"
  },
  {
    "id": "/service/board/jirum/19225710?od=T31&po=0&category=0&groupCd=",
    "site": "clien",
    "title": "[에픽게임즈] Keepup Survival 무료",
    "url": "https://www.clien.net/service/board/jirum/19225710?od=T31&po=0&category=0&groupCd=",
    "thumb": "https://edgio.clien.net/F01/2026/7/15775048/331417be36953c.jpg?scale=width:480",
    "score": 4551,
    "views": 4551,
    "crawled_at": "2026-07-13T15:42:50.991996+00:00"
  },
  {
    "id": "/service/board/jirum/19225729?od=T31&po=0&category=0&groupCd=",
    "site": "clien",
    "title": "[WearOS] SamWatch Simple Tenth 2025 일시 무료",
    "url": "https://www.clien.net/service/board/jirum/19225729?od=T31&po=0&category=0&groupCd=",
    "thumb": "https://edgio.clien.net/F01/2026/7/15775074/331e40ff732842.png?scale=width:480",
    "score": 2989,
    "views": 2989,
    "crawled_at": "2026-07-13T15:42:50.991996+00:00"
  },
  {
    "id": "/service/board/jirum/19226344?od=T31&po=0&category=0&groupCd=",
    "site": "clien",
    "title": "[Android] Metal Soldiers 4 Pro 일시 무료",
    "url": "https://www.clien.net/service/board/jirum/19226344?od=T31&po=0&category=0&groupCd=",
    "thumb": "https://edgio.clien.net/F01/2026/7/15775688/334dfde85c1519.webp?scale=width:480",
    "score": 1984,
    "views": 1984,
    "crawled_at": "2026-07-13T15:42:50.991996+00:00"
  },
  {
    "id": "1020",
    "site": "ruliweb",
    "title": "[네이버페이] 15원(10)",
    "url": "https://bbs.ruliweb.com/market/board/1020/read/105593?",
    "thumb": null,
    "score": 117,
    "views": 22111,
    "crawled_at": "2026-07-13T15:42:50.991996+00:00"
  },
  {
    "id": "1020",
    "site": "ruliweb",
    "title": "[홈플러스] 전 점포 임시 휴업(60)",
    "url": "https://bbs.ruliweb.com/market/board/1020/read/105607?",
    "thumb": null,
    "score": 57,
    "views": 48334,
    "crawled_at": "2026-07-13T15:42:50.991996+00:00"
  },
  {
    "id": "303158",
    "site": "ppomppu",
    "title": "[올영] 이즈앤트리 어니언 플루이드 썬크림 50ml 마지막 물량(3,800원/84%/유배)",
    "url": "https://www.ppomppu.co.kr/zboard/zboard/view.php?id=pmarket&&no=303158",
    "thumb": "https://cdn2.ppomppu.co.kr/zboard/data/_thumb/pmarket/8/small_303158.jpg",
    "score": 53,
    "views": 3419,
    "crawled_at": "2026-07-13T15:42:50.991996+00:00"
  },
  {
    "id": "1020",
    "site": "ruliweb",
    "title": "[네이버페이] 라방 5원(7)",
    "url": "https://bbs.ruliweb.com/market/board/1020/read/105592?",
    "thumb": null,
    "score": 43,
    "views": 20716,
    "crawled_at": "2026-07-13T15:42:50.991996+00:00"
  },
  {
    "id": "1020",
    "site": "ruliweb",
    "title": "[네이버페이] 일일적립, 클릭 24원, 라이브예고 16원(8)",
    "url": "https://bbs.ruliweb.com/market/board/1020/read/105615?",
    "thumb": null,
    "score": 39,
    "views": 2487,
    "crawled_at": "2026-07-13T15:42:50.991996+00:00"
  },
  {
    "id": "1020",
    "site": "ruliweb",
    "title": "[네이버페이] 일일적립, 클릭 24원, 라이브예고 16원",
    "url": "https://bbs.ruliweb.com/market/board/1020/read/105615?",
    "thumb": null,
    "score": 38,
    "views": 2368,
    "crawled_at": "2026-07-13T15:42:50.991996+00:00"
  },
  {
    "id": "1020",
    "site": "ruliweb",
    "title": "[맥도날드] 손흥민컵+빅맥세트 8900원 (7/13~)(29)",
    "url": "https://bbs.ruliweb.com/market/board/1020/read/105590?",
    "thumb": null,
    "score": 21,
    "views": 43887,
    "crawled_at": "2026-07-13T15:42:50.991996+00:00"
  },
  {
    "id": "1020",
    "site": "ruliweb",
    "title": "[한국닌텐도] 닌텐도 스위치 온라인 7일 체험권 (무료/현재 미구독자만)(1)",
    "url": "https://bbs.ruliweb.com/market/board/1020/read/105598?",
    "thumb": null,
    "score": 20,
    "views": 20191,
    "crawled_at": "2026-07-13T15:42:50.991996+00:00"
  },
  {
    "id": "1020",
    "site": "ruliweb",
    "title": "[쿠팡 생존]ASUS ROG XBOX ALLY X [1,207,070원]",
    "url": "https://bbs.ruliweb.com/market/board/1020/read/105613?",
    "thumb": null,
    "score": 16,
    "views": 15855,
    "crawled_at": "2026-07-13T15:42:50.991996+00:00"
  },
  {
    "id": "1020",
    "site": "ruliweb",
    "title": "[쿠팡 생존]ASUS ROG XBOX ALLY X [1,207,070원](61)",
    "url": "https://bbs.ruliweb.com/market/board/1020/read/105613?",
    "thumb": null,
    "score": 16,
    "views": 15908,
    "crawled_at": "2026-07-13T15:42:50.991996+00:00"
  },
  {
    "id": "1020",
    "site": "ruliweb",
    "title": "[Android] Metal Soldiers 4 Pro 무료",
    "url": "https://bbs.ruliweb.com/market/board/1020/read/105612?",
    "thumb": null,
    "score": 15,
    "views": 9983,
    "crawled_at": "2026-07-13T15:42:50.991996+00:00"
  },
  {
    "id": "1020",
    "site": "ruliweb",
    "title": "[Android] Metal Soldiers 4 Pro 무료(6)",
    "url": "https://bbs.ruliweb.com/market/board/1020/read/105612?",
    "thumb": null,
    "score": 15,
    "views": 10027,
    "crawled_at": "2026-07-13T15:42:50.991996+00:00"
  },
  {
    "id": "1020",
    "site": "ruliweb",
    "title": "[한국닌텐도] 닌텐도 공홈 스위치2 본체 기본형 648,000원(26)",
    "url": "https://bbs.ruliweb.com/market/board/1020/read/105599?",
    "thumb": null,
    "score": 14,
    "views": 28737,
    "crawled_at": "2026-07-13T15:42:50.991996+00:00"
  },
  {
    "id": "1020",
    "site": "ruliweb",
    "title": "[알리]이어폰,amp 등등 가격다양(2)",
    "url": "https://bbs.ruliweb.com/market/board/1020/read/105610?",
    "thumb": null,
    "score": 12,
    "views": 7113,
    "crawled_at": "2026-07-13T15:42:50.991996+00:00"
  },
  {
    "id": "1020",
    "site": "ruliweb",
    "title": "[롯데온] 농심 작은컵 신라면,새우탕,오짬,튀김우동 24개 (18,360...(12)",
    "url": "https://bbs.ruliweb.com/market/board/1020/read/105597?",
    "thumb": null,
    "score": 11,
    "views": 14808,
    "crawled_at": "2026-07-13T15:42:50.991996+00:00"
  },
  {
    "id": "1020",
    "site": "ruliweb",
    "title": "[닌텐도eShop] 파이널 판타지 7 리메이크 인터그레이드 DL 17,4...(3)",
    "url": "https://bbs.ruliweb.com/market/board/1020/read/105596?",
    "thumb": null,
    "score": 11,
    "views": 19828,
    "crawled_at": "2026-07-13T15:42:50.991996+00:00"
  },
  {
    "id": "1020",
    "site": "ruliweb",
    "title": "[쿠팡] 코카콜라 제로제로 350ml 24개 (와우회원 11,830원/무...(11)",
    "url": "https://bbs.ruliweb.com/market/board/1020/read/105594?",
    "thumb": null,
    "score": 10,
    "views": 13638,
    "crawled_at": "2026-07-13T15:42:50.991996+00:00"
  },
  {
    "id": "719646",
    "site": "ppomppu",
    "title": "크리넥스 3겹 순수알로에 28Mx24롤x2팩 (24,440원/무배)",
    "url": "https://www.ppomppu.co.kr/zboard/view.php?id=ppomppu&page=1&divpage=114&no=719646",
    "thumb": "https://cdn2.ppomppu.co.kr/zboard/data/_thumb/ppomppu/6/small_719646.jpg?t=20260714",
    "score": 9,
    "views": 9898,
    "crawled_at": "2026-07-13T15:42:50.991996+00:00"
  },
  {
    "id": "1020",
    "site": "ruliweb",
    "title": "[G마켓] 조지아 오리지널 240ml 30캔 (11,930원 / 무배)(3)",
    "url": "https://bbs.ruliweb.com/market/board/1020/read/105609?",
    "thumb": null,
    "score": 9,
    "views": 4237,
    "crawled_at": "2026-07-13T15:42:50.991996+00:00"
  },
  {
    "id": "1020",
    "site": "ruliweb",
    "title": "[지마켓] 오리온 포카칩 어니언 10봉+오리지널 10봉 (20,680원/...(3)",
    "url": "https://bbs.ruliweb.com/market/board/1020/read/105602?",
    "thumb": null,
    "score": 9,
    "views": 9558,
    "crawled_at": "2026-07-13T15:42:50.991996+00:00"
  },
  {
    "id": "1020",
    "site": "ruliweb",
    "title": "[롯데ON] 펩시콜라 제로슈거 라임향355ml 48캔 26,580원",
    "url": "https://bbs.ruliweb.com/market/board/1020/read/105611?",
    "thumb": null,
    "score": 8,
    "views": 3455,
    "crawled_at": "2026-07-13T15:42:50.991996+00:00"
  },
  {
    "id": "1020",
    "site": "ruliweb",
    "title": "[롯데ON] 펩시콜라 제로슈거 라임향355ml 48캔 26,580원",
    "url": "https://bbs.ruliweb.com/market/board/1020/read/105611?",
    "thumb": null,
    "score": 8,
    "views": 3582,
    "crawled_at": "2026-07-13T15:42:50.991996+00:00"
  },
  {
    "id": "1020",
    "site": "ruliweb",
    "title": "[컬리] 스위치 2 본체 + 젤다의 전설 티어스 오브 더 킹덤(732,8...(5)",
    "url": "https://bbs.ruliweb.com/market/board/1020/read/105603?",
    "thumb": null,
    "score": 8,
    "views": 9804,
    "crawled_at": "2026-07-13T15:42:50.991996+00:00"
  },
  {
    "id": "1020",
    "site": "ruliweb",
    "title": "[쿠팡] 펩시제로슈거 라임향 210ml 30캔(와우회원 11,560원/무...(3)",
    "url": "https://bbs.ruliweb.com/market/board/1020/read/105591?",
    "thumb": null,
    "score": 7,
    "views": 7050,
    "crawled_at": "2026-07-13T15:42:50.991996+00:00"
  },
  {
    "id": "1020",
    "site": "ruliweb",
    "title": "[지마켓]몬스터 에너지 울트라 500ml 24캔 (33,600원/무배)(12)",
    "url": "https://bbs.ruliweb.com/market/board/1020/read/105601?",
    "thumb": null,
    "score": 5,
    "views": 4911,
    "crawled_at": "2026-07-13T15:42:50.991996+00:00"
  },
  {
    "id": "1020",
    "site": "ruliweb",
    "title": "[지마켓] 코카콜라 490ml 12캔 + 아크릴키링 (7,900원/무료)(10)",
    "url": "https://bbs.ruliweb.com/market/board/1020/read/105595?",
    "thumb": null,
    "score": 5,
    "views": 10719,
    "crawled_at": "2026-07-13T15:42:50.991996+00:00"
  },
  {
    "id": "1020",
    "site": "ruliweb",
    "title": "[겜우리] NS2 소닉 프론티어 디피니티브 에디션 예판 / 54,800원(6)",
    "url": "https://bbs.ruliweb.com/market/board/1020/read/105608?",
    "thumb": null,
    "score": 4,
    "views": 8501,
    "crawled_at": "2026-07-13T15:42:50.991996+00:00"
  },
  {
    "id": "1020",
    "site": "ruliweb",
    "title": "[카톡선물하기] 스위치2 + 스위치2 젤다의전설 왕눈 732,800 원(8)",
    "url": "https://bbs.ruliweb.com/market/board/1020/read/105605?",
    "thumb": null,
    "score": 4,
    "views": 8348,
    "crawled_at": "2026-07-13T15:42:50.991996+00:00"
  },
  {
    "id": "1020",
    "site": "ruliweb",
    "title": "[롯데온] 칸타타파우치 3종 190ml 20팩 (8,580원/무료)(7)",
    "url": "https://bbs.ruliweb.com/market/board/1020/read/105600?",
    "thumb": null,
    "score": 4,
    "views": 6130,
    "crawled_at": "2026-07-13T15:42:50.991996+00:00"
  },
  {
    "id": "719914",
    "site": "ppomppu",
    "title": "쏭징 대용량 28L 저소음 제습기 SJ-388E(187,900원/무료)",
    "url": "https://www.ppomppu.co.kr/zboard/view.php?id=ppomppu&page=1&divpage=114&no=719914",
    "thumb": "https://cdn2.ppomppu.co.kr/zboard/data/_thumb/ppomppu/4/small_719914.jpg?t=20260714",
    "score": 3,
    "views": 7646,
    "crawled_at": "2026-07-13T15:42:50.991996+00:00"
  },
  {
    "id": "1020",
    "site": "ruliweb",
    "title": "[알리]카멜마운트 이동형 모니터 스탠드 86인치 가능(91,923원/무료...(5)",
    "url": "https://bbs.ruliweb.com/market/board/1020/read/105614?",
    "thumb": null,
    "score": 3,
    "views": 4087,
    "crawled_at": "2026-07-13T15:42:50.991996+00:00"
  },
  {
    "id": "1020",
    "site": "ruliweb",
    "title": "[반다이몰] S.H.몬스터아츠 에반게리온 초호기 G 각성 형태 / 192...(8)",
    "url": "https://bbs.ruliweb.com/market/board/1020/read/105604?",
    "thumb": null,
    "score": 3,
    "views": 9045,
    "crawled_at": "2026-07-13T15:42:50.991996+00:00"
  },
  {
    "id": "49451",
    "site": "ppomppu",
    "title": "이마트 16일부터 달갈 파격할인하네요",
    "url": "https://www.ppomppu.co.kr/zboard/zboard/view.php?id=social&no=49451",
    "thumb": "https://cdn2.ppomppu.co.kr/zboard/data3/2026/0713/20260713200948_0IocgOwDPl.jpg",
    "score": 2,
    "views": 3254,
    "crawled_at": "2026-07-13T15:42:50.991996+00:00"
  },
  {
    "id": "303156",
    "site": "ppomppu",
    "title": "[토스] 스파클 생수, 무라벨, 500ml, 80개 (7,840원/무배)",
    "url": "https://www.ppomppu.co.kr/zboard/zboard/view.php?id=pmarket&&no=303156",
    "thumb": "https://cdn2.ppomppu.co.kr/zboard/data/_thumb/pmarket/6/small_303156.jpg",
    "score": 1,
    "views": 1547,
    "crawled_at": "2026-07-13T15:42:50.991996+00:00"
  },
  {
    "id": "1020",
    "site": "ruliweb",
    "title": "[네이버] 더미식 당찬진미 백미밥 200g 24개 (19,850원/무료)",
    "url": "https://bbs.ruliweb.com/market/board/1020/read/105616?",
    "thumb": null,
    "score": 1,
    "views": 555,
    "crawled_at": "2026-07-13T15:42:50.991996+00:00"
  },
  {
    "id": "719933",
    "site": "ppomppu",
    "title": "포스트 아몬드후레이크 620g 외 3봉+랜덤 증정 (13,780원/무료)",
    "url": "https://www.ppomppu.co.kr/zboard/view.php?id=ppomppu&page=1&divpage=114&no=719933",
    "thumb": "https://cdn2.ppomppu.co.kr/zboard/data/_thumb/ppomppu/3/small_719933.jpg?t=20260714",
    "score": 0,
    "views": 58,
    "crawled_at": "2026-07-13T15:42:50.991996+00:00"
  },
  {
    "id": "719932",
    "site": "ppomppu",
    "title": "락토페린 글루타치온 비타민C 60정 / (5900원/16900원이상구매시무료배송)",
    "url": "https://www.ppomppu.co.kr/zboard/view.php?id=ppomppu&page=1&divpage=114&no=719932",
    "thumb": "https://cdn2.ppomppu.co.kr/zboard/data/_thumb/ppomppu/2/small_719932.jpg?t=20260714",
    "score": 0,
    "views": 136,
    "crawled_at": "2026-07-13T15:42:50.991996+00:00"
  },
  {
    "id": "719931",
    "site": "ppomppu",
    "title": "투게더 엑설런트 요맘때 3+2개 골라담기(18,540원/무료)",
    "url": "https://www.ppomppu.co.kr/zboard/view.php?id=ppomppu&page=1&divpage=114&no=719931",
    "thumb": "https://cdn2.ppomppu.co.kr/zboard/data/_thumb/ppomppu/1/small_719931.jpg?t=20260714",
    "score": 0,
    "views": 294,
    "crawled_at": "2026-07-13T15:42:50.991996+00:00"
  },
  {
    "id": "719930",
    "site": "ppomppu",
    "title": "백도 딱딱이 복숭아 중과 4kg (15,200원/무료)",
    "url": "https://www.ppomppu.co.kr/zboard/view.php?id=ppomppu&page=1&divpage=114&no=719930",
    "thumb": "https://cdn2.ppomppu.co.kr/zboard/data/_thumb/ppomppu/0/small_719930.jpg?t=20260714",
    "score": 0,
    "views": 251,
    "crawled_at": "2026-07-13T15:42:50.991996+00:00"
  },
  {
    "id": "719929",
    "site": "ppomppu",
    "title": "삼다수 2L 24개 (18,920원/무료)",
    "url": "https://www.ppomppu.co.kr/zboard/view.php?id=ppomppu&page=1&divpage=114&no=719929",
    "thumb": "https://cdn2.ppomppu.co.kr/zboard/data/_thumb/ppomppu/9/small_719929.jpg?t=20260714",
    "score": 0,
    "views": 391,
    "crawled_at": "2026-07-13T15:42:50.991996+00:00"
  },
  {
    "id": "719928",
    "site": "ppomppu",
    "title": "카스 제로 무알코올 음료 350ml 24개 (19,000원/무료)",
    "url": "https://www.ppomppu.co.kr/zboard/view.php?id=ppomppu&page=1&divpage=114&no=719928",
    "thumb": "https://cdn2.ppomppu.co.kr/zboard/data/_thumb/ppomppu/8/small_719928.jpg?t=20260714",
    "score": 0,
    "views": 316,
    "crawled_at": "2026-07-13T15:42:50.991996+00:00"
  },
  {
    "id": "719927",
    "site": "ppomppu",
    "title": "컨셉원 와플 반팔 카라티 (15,900원/무료)",
    "url": "https://www.ppomppu.co.kr/zboard/view.php?id=ppomppu&page=1&divpage=114&no=719927",
    "thumb": "https://cdn2.ppomppu.co.kr/zboard/data/_thumb/ppomppu/7/small_719927.jpg?t=20260714",
    "score": 0,
    "views": 817,
    "crawled_at": "2026-07-13T15:42:50.991996+00:00"
  },
  {
    "id": "719926",
    "site": "ppomppu",
    "title": "한돈 1+등급 뒷고기 500g 2팩 (10,900원/무료)",
    "url": "https://www.ppomppu.co.kr/zboard/view.php?id=ppomppu&page=1&divpage=114&no=719926",
    "thumb": "https://cdn2.ppomppu.co.kr/zboard/data/_thumb/ppomppu/6/small_719926.jpg?t=20260714",
    "score": 0,
    "views": 572,
    "crawled_at": "2026-07-13T15:42:50.991996+00:00"
  },
  {
    "id": "719925",
    "site": "ppomppu",
    "title": "퍼실 2.0 라벤더 6개+퍼실 300ml 증정 (50,614원/무배)",
    "url": "https://www.ppomppu.co.kr/zboard/view.php?id=ppomppu&page=1&divpage=114&no=719925",
    "thumb": "https://cdn2.ppomppu.co.kr/zboard/data/_thumb/ppomppu/5/small_719925.jpg?t=20260714",
    "score": 0,
    "views": 547,
    "crawled_at": "2026-07-13T15:42:50.991996+00:00"
  },
  {
    "id": "719924",
    "site": "ppomppu",
    "title": "할리스 카페라떼 2팩 (16,990원/무료)",
    "url": "https://www.ppomppu.co.kr/zboard/view.php?id=ppomppu&page=1&divpage=114&no=719924",
    "thumb": "https://cdn2.ppomppu.co.kr/zboard/data/_thumb/ppomppu/4/small_719924.jpg?t=20260714",
    "score": 0,
    "views": 585,
    "crawled_at": "2026-07-13T15:42:50.991996+00:00"
  },
  {
    "id": "719923",
    "site": "ppomppu",
    "title": "탑스텝 얼룩제거제 500ml 2개 (9,600원/무료)",
    "url": "https://www.ppomppu.co.kr/zboard/view.php?id=ppomppu&page=1&divpage=114&no=719923",
    "thumb": "https://cdn2.ppomppu.co.kr/zboard/data/_thumb/ppomppu/3/small_719923.jpg?t=20260714",
    "score": 0,
    "views": 469,
    "crawled_at": "2026-07-13T15:42:50.991996+00:00"
  },
  {
    "id": "719922",
    "site": "ppomppu",
    "title": "에코센스 트라이탄 밀폐용기 조이락 체험특가 (9,900원/무료)",
    "url": "https://www.ppomppu.co.kr/zboard/view.php?id=ppomppu&page=1&divpage=114&no=719922",
    "thumb": "https://cdn2.ppomppu.co.kr/zboard/data/_thumb/ppomppu/2/small_719922.jpg?t=20260714",
    "score": 0,
    "views": 522,
    "crawled_at": "2026-07-13T15:42:50.991996+00:00"
  },
  {
    "id": "719921",
    "site": "ppomppu",
    "title": "도루코 페이스7투 프레시 스타터킷+증정포함 (15,610원/무료)",
    "url": "https://www.ppomppu.co.kr/zboard/view.php?id=ppomppu&page=1&divpage=114&no=719921",
    "thumb": "https://cdn2.ppomppu.co.kr/zboard/data/_thumb/ppomppu/1/small_719921.jpg?t=20260714",
    "score": 0,
    "views": 463,
    "crawled_at": "2026-07-13T15:42:50.991996+00:00"
  },
  {
    "id": "719920",
    "site": "ppomppu",
    "title": "완도산 활전복 1kg 12~14미 (16,370원/무배)",
    "url": "https://www.ppomppu.co.kr/zboard/view.php?id=ppomppu&page=1&divpage=114&no=719920",
    "thumb": "https://cdn2.ppomppu.co.kr/zboard/data/_thumb/ppomppu/0/small_719920.jpg?t=20260714",
    "score": 0,
    "views": 342,
    "crawled_at": "2026-07-13T15:42:50.991996+00:00"
  },
  {
    "id": "719919",
    "site": "ppomppu",
    "title": "습기제거제 라벤더향 250g 18개입 (13,520원/무료)",
    "url": "https://www.ppomppu.co.kr/zboard/view.php?id=ppomppu&page=1&divpage=114&no=719919",
    "thumb": "https://cdn2.ppomppu.co.kr/zboard/data/_thumb/ppomppu/9/small_719919.jpg?t=20260714",
    "score": 0,
    "views": 466,
    "crawled_at": "2026-07-13T15:42:50.991996+00:00"
  },
  {
    "id": "719918",
    "site": "ppomppu",
    "title": "용왕해신탕 (닭+전복+문어+새우+약재) 3~4인분 햇썹 당일제조(26,590/무배)",
    "url": "https://www.ppomppu.co.kr/zboard/view.php?id=ppomppu&page=1&divpage=114&no=719918",
    "thumb": "https://cdn2.ppomppu.co.kr/zboard/data/_thumb/ppomppu/8/small_719918.jpg?t=20260714",
    "score": 0,
    "views": 604,
    "crawled_at": "2026-07-13T15:42:50.991996+00:00"
  },
  {
    "id": "719917",
    "site": "ppomppu",
    "title": "크리넥스 데코소프트 28m 24롤 2팩 + 마이비데 (29,200원 / 무료)",
    "url": "https://www.ppomppu.co.kr/zboard/view.php?id=ppomppu&page=1&divpage=114&no=719917",
    "thumb": "https://cdn2.ppomppu.co.kr/zboard/data/_thumb/ppomppu/7/small_719917.jpg?t=20260714",
    "score": 0,
    "views": 3242,
    "crawled_at": "2026-07-13T15:42:50.991996+00:00"
  },
  {
    "id": "719916",
    "site": "ppomppu",
    "title": "파워에이드 마운틴블라스트 900ml, 12개 (티멤 10,830원/무료)",
    "url": "https://www.ppomppu.co.kr/zboard/view.php?id=ppomppu&page=1&divpage=114&no=719916",
    "thumb": "https://cdn2.ppomppu.co.kr/zboard/data/_thumb/ppomppu/6/small_719916.jpg?t=20260714",
    "score": 0,
    "views": 1350,
    "crawled_at": "2026-07-13T15:42:50.991996+00:00"
  },
  {
    "id": "719915",
    "site": "ppomppu",
    "title": "써머텍트 러닝 헤어밴드 1+1 (9,570원/무료)",
    "url": "https://www.ppomppu.co.kr/zboard/view.php?id=ppomppu&page=1&divpage=114&no=719915",
    "thumb": "https://cdn2.ppomppu.co.kr/zboard/data/_thumb/ppomppu/5/small_719915.jpg?t=20260714",
    "score": 0,
    "views": 2623,
    "crawled_at": "2026-07-13T15:42:50.991996+00:00"
  },
  {
    "id": "303157",
    "site": "ppomppu",
    "title": "[네이버] 보일링 시푸드 밀키드 / 크리에이티브 PEBBLE V2 스피커",
    "url": "https://www.ppomppu.co.kr/zboard/zboard/view.php?id=pmarket&&no=303157",
    "thumb": "https://cdn2.ppomppu.co.kr/zboard/data/_thumb/pmarket/7/small_303157.jpg",
    "score": 0,
    "views": 1258,
    "crawled_at": "2026-07-13T15:42:50.991996+00:00"
  },
  {
    "id": "49453",
    "site": "ppomppu",
    "title": "장호원 햇사레 복숭아 맛있네요",
    "url": "https://www.ppomppu.co.kr/zboard/zboard/view.php?id=social&no=49453",
    "thumb": "https://cdn2.ppomppu.co.kr/zboard/data3/2026/0713/20260713220444_m11abfpUfR.png",
    "score": 0,
    "views": 723,
    "crawled_at": "2026-07-13T15:42:50.991996+00:00"
  },
  {
    "id": "49452",
    "site": "ppomppu",
    "title": "[옥션] 홀리지 여름 패션잡화 모자/가방/양말/스카프/양산 외 할인 모음전 (4,880원~/무배)",
    "url": "https://www.ppomppu.co.kr/zboard/zboard/view.php?id=social&no=49452",
    "thumb": "https://cdn2.ppomppu.co.kr/zboard/data3/2026/0713/20260713181523_CbSpTO0TPf.jpg",
    "score": 0,
    "views": 699,
    "crawled_at": "2026-07-13T15:42:50.991996+00:00"
  }
]