[
  {
    "id": "/service/board/jirum/19204025?od=T31&po=0&category=0&groupCd=",
    "site": "clien",
    "title": "[iOS] Street Fighter IV CE (1,500원)",
    "url": "https://www.clien.net/service/board/jirum/19204025?od=T31&po=0&category=0&groupCd=",
    "thumb": "https://edgio.clien.net/F01/2026/6/15745766/27c88fd99fef20.webp?scale=width:480",
    "score": 135000,
    "views": 135000,
    "crawled_at": "2026-06-10T21:35:37.062078+00:00"
  },
  {
    "id": "/service/board/jirum/19203373?od=T31&po=0&category=0&groupCd=",
    "site": "clien",
    "title": "[iOS] Battery Life Health: Pro Check 일시 무료",
    "url": "https://www.clien.net/service/board/jirum/19203373?od=T31&po=0&category=0&groupCd=",
    "thumb": "https://edgio.clien.net/F01/2026/6/15745057/10c443c0dedda7.jpeg?scale=width:480",
    "score": 126000,
    "views": 126000,
    "crawled_at": "2026-06-10T21:35:37.062078+00:00"
  },
  {
    "id": "/service/board/jirum/19204631?od=T31&po=0&category=0&groupCd=",
    "site": "clien",
    "title": "[iOS] Zee Cast 리딤",
    "url": "https://www.clien.net/service/board/jirum/19204631?od=T31&po=0&category=0&groupCd=",
    "thumb": "https://edgio.clien.net/F01/2026/6/15746606/280fb60adfe02a.webp?scale=width:480",
    "score": 117000,
    "views": 117000,
    "crawled_at": "2026-06-10T21:35:37.062078+00:00"
  },
  {
    "id": "/service/board/jirum/19203040?od=T31&po=0&category=0&groupCd=",
    "site": "clien",
    "title": "[스팀] Overcome Your Fears - Caretaker 일시 무료",
    "url": "https://www.clien.net/service/board/jirum/19203040?od=T31&po=0&category=0&groupCd=",
    "thumb": "https://edgio.clien.net/F01/2026/6/15744738/10a878dc1ebfca.jpeg?scale=width:480",
    "score": 112000,
    "views": 112000,
    "crawled_at": "2026-06-10T21:35:37.062078+00:00"
  },
  {
    "id": "/service/board/jirum/19204465?od=T31&po=0&category=0&groupCd=",
    "site": "clien",
    "title": "[끌올/이베이] 안경형 디스플레이 VITURE PRO XR 리퍼 (143.2불)",
    "url": "https://www.clien.net/service/board/jirum/19204465?od=T31&po=0&category=0&groupCd=",
    "thumb": "https://edgio.clien.net/F01/2026/6/15746347/e49c3b394e58d.webp?scale=width:480",
    "score": 111000,
    "views": 111000,
    "crawled_at": "2026-06-10T21:35:37.062078+00:00"
  },
  {
    "id": "/service/board/jirum/19204325?od=T31&po=0&category=0&groupCd=",
    "site": "clien",
    "title": "[Android] PDF Reader & Editor (PRO) 일시 무료",
    "url": "https://www.clien.net/service/board/jirum/19204325?od=T31&po=0&category=0&groupCd=",
    "thumb": "https://edgio.clien.net/F01/2026/6/15746126/afcd00f47fd85.png?scale=width:480",
    "score": 107000,
    "views": 107000,
    "crawled_at": "2026-06-10T21:35:37.062078+00:00"
  },
  {
    "id": "/service/board/jirum/19203965?od=T31&po=0&category=0&groupCd=",
    "site": "clien",
    "title": "[에픽게임즈] Rogue Waters 일시 무료",
    "url": "https://www.clien.net/service/board/jirum/19203965?od=T31&po=0&category=0&groupCd=",
    "thumb": "https://edgio.clien.net/F01/2026/6/15745642/27bcd1965cdd60.webp?scale=width:480",
    "score": 106000,
    "views": 106000,
    "crawled_at": "2026-06-10T21:35:37.062078+00:00"
  },
  {
    "id": "/service/board/jirum/19203966?od=T31&po=0&category=0&groupCd=",
    "site": "clien",
    "title": "[WearOS] Tag Connected watch face외 일시 무료",
    "url": "https://www.clien.net/service/board/jirum/19203966?od=T31&po=0&category=0&groupCd=",
    "thumb": "https://edgio.clien.net/F01/2026/6/15745644/27bd45385ab6dc.png?scale=width:480",
    "score": 9763,
    "views": 9763,
    "crawled_at": "2026-06-10T21:35:37.062078+00:00"
  },
  {
    "id": "/service/board/jirum/19203718?od=T31&po=0&category=0&groupCd=",
    "site": "clien",
    "title": "종료 [iOS] Widgetik: 홈 화면 위젯 일시 무료",
    "url": "https://www.clien.net/service/board/jirum/19203718?od=T31&po=0&category=0&groupCd=",
    "thumb": "https://edgio.clien.net/F01/2026/6/15745310/df8d89e73fe58.jpeg?scale=width:480",
    "score": 9638,
    "views": 9638,
    "crawled_at": "2026-06-10T21:35:37.062078+00:00"
  },
  {
    "id": "/service/board/jirum/19203744?od=T31&po=0&category=0&groupCd=",
    "site": "clien",
    "title": "생활공작소 욕실용 세정제 750ml 3개 4,500원",
    "url": "https://www.clien.net/service/board/jirum/19203744?od=T31&po=0&category=0&groupCd=",
    "thumb": "https://edgio.clien.net/F01/2026/6/15745344/27a5b513e094f0.jpg?scale=width:480",
    "score": 9612,
    "views": 9612,
    "crawled_at": "2026-06-10T21:35:37.062078+00:00"
  },
  {
    "id": "/service/board/jirum/19203237?od=T31&po=0&category=0&groupCd=",
    "site": "clien",
    "title": "[스팀]Digimon Story Time Stranger 40% 할인",
    "url": "https://www.clien.net/service/board/jirum/19203237?od=T31&po=0&category=0&groupCd=",
    "thumb": "https://edgio.clien.net/F01/2026/6/15744970/a9d8ae4c87155.jpg?scale=width:480",
    "score": 9498,
    "views": 9498,
    "crawled_at": "2026-06-10T21:35:37.062078+00:00"
  },
  {
    "id": "/service/board/jirum/19204697?od=T31&po=0&category=0&groupCd=",
    "site": "clien",
    "title": "[MacOS] Shortcuts App : QuickLinks 일시 무료",
    "url": "https://www.clien.net/service/board/jirum/19204697?od=T31&po=0&category=0&groupCd=",
    "thumb": "https://edgio.clien.net/F01/2026/6/15746733/28209b4d250a01.jpeg?scale=width:480",
    "score": 9467,
    "views": 9467,
    "crawled_at": "2026-06-10T21:35:37.062078+00:00"
  },
  {
    "id": "/service/board/jirum/19204629?od=T31&po=0&category=0&groupCd=",
    "site": "clien",
    "title": "[Duolingo] 듀오 링고 슈퍼 1개월 무료 리딤",
    "url": "https://www.clien.net/service/board/jirum/19204629?od=T31&po=0&category=0&groupCd=",
    "thumb": "https://edgio.clien.net/F01/2026/6/15746605/b22c48ba2e2fa.jpeg?scale=width:480",
    "score": 8531,
    "views": 8531,
    "crawled_at": "2026-06-10T21:35:37.062078+00:00"
  },
  {
    "id": "/service/board/jirum/19204240?od=T31&po=0&category=0&groupCd=",
    "site": "clien",
    "title": "[bandcamp] Edgar Wasser “Neurodiversitäter EP 음반 무료",
    "url": "https://www.clien.net/service/board/jirum/19204240?od=T31&po=0&category=0&groupCd=",
    "thumb": "https://edgio.clien.net/F01/2026/6/15746003/27de84b8706b0a.jpeg?scale=width:480",
    "score": 8370,
    "views": 8370,
    "crawled_at": "2026-06-10T21:35:37.062078+00:00"
  },
  {
    "id": "/service/board/jirum/19205404?od=T31&po=0&category=0&groupCd=",
    "site": "clien",
    "title": "[ComputerBild] Password Depot 18 무료",
    "url": "https://www.clien.net/service/board/jirum/19205404?od=T31&po=0&category=0&groupCd=",
    "thumb": "https://edgio.clien.net/F01/2026/6/15747658/11af8300995302.webp?scale=width:480",
    "score": 8169,
    "views": 8169,
    "crawled_at": "2026-06-10T21:35:37.062078+00:00"
  },
  {
    "id": "/service/board/jirum/19205827?od=T31&po=0&category=0&groupCd=",
    "site": "clien",
    "title": "[iOS] Manfredo Run, KungFuBack & MagicKit Pro 일시 무료",
    "url": "https://www.clien.net/service/board/jirum/19205827?od=T31&po=0&category=0&groupCd=",
    "thumb": "https://edgio.clien.net/F01/2026/6/15748172/11e484d4986e3c.png?scale=width:480",
    "score": 7893,
    "views": 7893,
    "crawled_at": "2026-06-10T21:35:37.062078+00:00"
  },
  {
    "id": "/service/board/jirum/19204911?od=T31&po=0&category=0&groupCd=",
    "site": "clien",
    "title": "[WearOS] HMKWatch Analog 265 일시 무료",
    "url": "https://www.clien.net/service/board/jirum/19204911?od=T31&po=0&category=0&groupCd=",
    "thumb": "https://edgio.clien.net/F01/2026/6/15746997/116d6092db1cbc.jpeg?scale=width:480",
    "score": 7759,
    "views": 7759,
    "crawled_at": "2026-06-10T21:35:37.062078+00:00"
  },
  {
    "id": "/service/board/jirum/19205302?od=T31&po=0&category=0&groupCd=",
    "site": "clien",
    "title": "삼성 Q9000 에어컨 17평 스탠드 AF60F17D11BS",
    "url": "https://www.clien.net/service/board/jirum/19205302?od=T31&po=0&category=0&groupCd=",
    "thumb": "https://edgio.clien.net/F01/2026/6/15747544/11aa8423111ee5.png?scale=width:480",
    "score": 7602,
    "views": 7602,
    "crawled_at": "2026-06-10T21:35:37.062078+00:00"
  },
  {
    "id": "/service/board/jirum/19205298?od=T31&po=0&category=0&groupCd=",
    "site": "clien",
    "title": "[스팀/GOG] Remothered: Tormented Fathers외 일시 무료",
    "url": "https://www.clien.net/service/board/jirum/19205298?od=T31&po=0&category=0&groupCd=",
    "thumb": "https://edgio.clien.net/F01/2026/6/15747535/11aa5eba6d3b25.jpeg?scale=width:480",
    "score": 6381,
    "views": 6381,
    "crawled_at": "2026-06-10T21:35:37.062078+00:00"
  },
  {
    "id": "/service/board/jirum/19206254?od=T31&po=0&category=0&groupCd=",
    "site": "clien",
    "title": "[iOS] BetterCast – 팟캐스트 플레이어 일시 무료",
    "url": "https://www.clien.net/service/board/jirum/19206254?od=T31&po=0&category=0&groupCd=",
    "thumb": "https://edgio.clien.net/F01/2026/6/15748730/120e8f19863bec.jpeg?scale=width:480",
    "score": 6192,
    "views": 6192,
    "crawled_at": "2026-06-10T21:35:37.062078+00:00"
  },
  {
    "id": "/service/board/jirum/19205213?od=T31&po=0&category=0&groupCd=",
    "site": "clien",
    "title": "[WearOS] Cockpit Watch Face A9외 일시 무료",
    "url": "https://www.clien.net/service/board/jirum/19205213?od=T31&po=0&category=0&groupCd=",
    "thumb": "https://edgio.clien.net/F01/2026/6/15747469/b84be8e7b1fbc.jpeg?scale=width:480",
    "score": 5757,
    "views": 5757,
    "crawled_at": "2026-06-10T21:35:37.062078+00:00"
  },
  {
    "id": "/service/board/jirum/19206185?od=T31&po=0&category=0&groupCd=",
    "site": "clien",
    "title": "[RARLab] WinRAR (13,178원)",
    "url": "https://www.clien.net/service/board/jirum/19206185?od=T31&po=0&category=0&groupCd=",
    "thumb": "https://edgio.clien.net/F01/2026/6/15748646/be64f5db4f658.jpeg?scale=width:480",
    "score": 5012,
    "views": 5012,
    "crawled_at": "2026-06-10T21:35:37.062078+00:00"
  },
  {
    "id": "/service/board/jirum/19206043?od=T31&po=0&category=0&groupCd=",
    "site": "clien",
    "title": "(할인코드 충전 완료!) [6월 쿨한 JUNE 혜택 프로모션 종료 D-1]",
    "url": "https://www.clien.net/service/board/jirum/19206043?od=T31&po=0&category=0&groupCd=",
    "thumb": null,
    "score": 4555,
    "views": 4555,
    "crawled_at": "2026-06-10T21:35:37.062078+00:00"
  },
  {
    "id": "/service/board/jirum/19206436?od=T31&po=0&category=0&groupCd=",
    "site": "clien",
    "title": "롯데리아 불고기 / 한우불고기버거 세트 10장(지류) 롯데카드",
    "url": "https://www.clien.net/service/board/jirum/19206436?od=T31&po=0&category=0&groupCd=",
    "thumb": "https://edgio.clien.net/F01/2026/6/15748927/122181fd9d6db8.jpg?scale=width:480",
    "score": 4346,
    "views": 4346,
    "crawled_at": "2026-06-10T21:35:37.062078+00:00"
  },
  {
    "id": "/service/board/jirum/19206447?od=T31&po=0&category=0&groupCd=",
    "site": "clien",
    "title": "천하장사 오리지날 1.5kg 2개 총 3kg (31,000원 / 무배)",
    "url": "https://www.clien.net/service/board/jirum/19206447?od=T31&po=0&category=0&groupCd=",
    "thumb": "https://edgio.clien.net/F01/2026/6/15748947/1222f933e21430.jpg?scale=width:480",
    "score": 4318,
    "views": 4318,
    "crawled_at": "2026-06-10T21:35:37.062078+00:00"
  },
  {
    "id": "/service/board/jirum/19206404?od=T31&po=0&category=0&groupCd=",
    "site": "clien",
    "title": "신라면 10봉 너구리 5봉 짜파게티 5봉 총 20봉 13,900원",
    "url": "https://www.clien.net/service/board/jirum/19206404?od=T31&po=0&category=0&groupCd=",
    "thumb": "https://edgio.clien.net/F01/2026/6/15748897/28e7282ce0ea6c.jpg?scale=width:480",
    "score": 4229,
    "views": 4229,
    "crawled_at": "2026-06-10T21:35:37.062078+00:00"
  },
  {
    "id": "/service/board/jirum/19206787?od=T31&po=0&category=0&groupCd=",
    "site": "clien",
    "title": "[WearOS] 이재명 대통령 취임 1주년 기념 워치페이스",
    "url": "https://www.clien.net/service/board/jirum/19206787?od=T31&po=0&category=0&groupCd=",
    "thumb": null,
    "score": 3389,
    "views": 3389,
    "crawled_at": "2026-06-10T21:35:37.062078+00:00"
  },
  {
    "id": "/service/board/jirum/19206621?od=T31&po=0&category=0&groupCd=",
    "site": "clien",
    "title": "[WearOS] Palette Watch Face외 일시 무료",
    "url": "https://www.clien.net/service/board/jirum/19206621?od=T31&po=0&category=0&groupCd=",
    "thumb": "https://edgio.clien.net/F01/2026/6/15749186/290e476a4844c1.jpeg?scale=width:480",
    "score": 3166,
    "views": 3166,
    "crawled_at": "2026-06-10T21:35:37.062078+00:00"
  },
  {
    "id": "/service/board/jirum/19206822?od=T31&po=0&category=0&groupCd=",
    "site": "clien",
    "title": "[WearOS] SamWatch Analog Omicron 3 2024 외 일시 무료",
    "url": "https://www.clien.net/service/board/jirum/19206822?od=T31&po=0&category=0&groupCd=",
    "thumb": "https://edgio.clien.net/F01/2026/6/15749368/c3332667e6924.png?scale=width:480",
    "score": 2842,
    "views": 2842,
    "crawled_at": "2026-06-10T21:35:37.062078+00:00"
  },
  {
    "id": "/service/board/jirum/19207045?od=T31&po=0&category=0&groupCd=",
    "site": "clien",
    "title": "[오늘의집] 매일두유 고단백 검은콩 190ml 48팩+6팩 (30,712원/무료)",
    "url": "https://www.clien.net/service/board/jirum/19207045?od=T31&po=0&category=0&groupCd=",
    "thumb": "https://edgio.clien.net/F01/2026/6/15749639/293093f12b6e15.jpg?scale=width:480",
    "score": 1748,
    "views": 1748,
    "crawled_at": "2026-06-10T21:35:37.062078+00:00"
  },
  {
    "id": "1020",
    "site": "ruliweb",
    "title": "[네이버페이] 일일적립, 클릭 72원, 라이브예고 9원",
    "url": "https://bbs.ruliweb.com/market/board/1020/read/104731?",
    "thumb": null,
    "score": 91,
    "views": 9431,
    "crawled_at": "2026-06-10T21:35:37.062078+00:00"
  },
  {
    "id": "1020",
    "site": "ruliweb",
    "title": "[네이버페이] 일일적립, 클릭 72원, 라이브예고 9원(12)",
    "url": "https://bbs.ruliweb.com/market/board/1020/read/104731?",
    "thumb": null,
    "score": 91,
    "views": 9447,
    "crawled_at": "2026-06-10T21:35:37.062078+00:00"
  },
  {
    "id": "302683",
    "site": "ppomppu",
    "title": "[네이버] 삼성전자 감사 페스티벌 LIVE 6월11일(11시) 삼성전자 Q9000 스탠드형 / 멀티형 / 6평 인버터 에어컨 / 75인치 QLED TV / 65인치 Mini LED TV",
    "url": "https://www.ppomppu.co.kr/zboard/zboard/view.php?id=pmarket&&no=302683",
    "thumb": "https://cdn2.ppomppu.co.kr/zboard/data/_thumb/pmarket/3/small_302683.jpg",
    "score": 54,
    "views": 5520,
    "crawled_at": "2026-06-10T21:35:37.062078+00:00"
  },
  {
    "id": "302681",
    "site": "ppomppu",
    "title": "[국민과 함께, 삼성전자 감사 페스티벌][G마켓 LIVE] 6/10일 21시! 가전 다품 LIVE! 삼성 감사 페스티벌!  삼성이 전하는 감사 페스티벌 혜택이 와르르르!!",
    "url": "https://www.ppomppu.co.kr/zboard/zboard/view.php?id=pmarket&&no=302681",
    "thumb": "https://cdn2.ppomppu.co.kr/zboard/data/_thumb/pmarket/1/small_302681.jpg",
    "score": 52,
    "views": 4737,
    "crawled_at": "2026-06-10T21:35:37.062078+00:00"
  },
  {
    "id": "302684",
    "site": "ppomppu",
    "title": "[G마켓] 갤럭시 자급제폰 대국민 감사제 S26 S26플러스 S26울트라 플립7 폴드7 S25FE A36 A17",
    "url": "https://www.ppomppu.co.kr/zboard/zboard/view.php?id=pmarket&&no=302684",
    "thumb": "https://cdn2.ppomppu.co.kr/zboard/data/_thumb/pmarket/4/small_302684.jpg",
    "score": 50,
    "views": 6346,
    "crawled_at": "2026-06-10T21:35:37.062078+00:00"
  },
  {
    "id": "1020",
    "site": "ruliweb",
    "title": "[쿠팡] 오리온 카스타드 12p 288g, 2개 / 4,500원 (와우무...(17)",
    "url": "https://bbs.ruliweb.com/market/board/1020/read/104718?",
    "thumb": null,
    "score": 23,
    "views": 21632,
    "crawled_at": "2026-06-10T21:35:37.062078+00:00"
  },
  {
    "id": "1020",
    "site": "ruliweb",
    "title": "[네이버] 인벤게임즈 몬스터헌터 바하 시리즈 세일 / 가격 다양(19)",
    "url": "https://bbs.ruliweb.com/market/board/1020/read/104722?",
    "thumb": null,
    "score": 20,
    "views": 29491,
    "crawled_at": "2026-06-10T21:35:37.062078+00:00"
  },
  {
    "id": "1020",
    "site": "ruliweb",
    "title": "[닌텐도공홈] 닌텐도 스위치 2 본체(24)",
    "url": "https://bbs.ruliweb.com/market/board/1020/read/104706?",
    "thumb": null,
    "score": 20,
    "views": 31085,
    "crawled_at": "2026-06-10T21:35:37.062078+00:00"
  },
  {
    "id": "1020",
    "site": "ruliweb",
    "title": "[한국관광공사] 인구소멸지역 숙박세일페스타 (11일 오전 10시~)(25)",
    "url": "https://bbs.ruliweb.com/market/board/1020/read/104726?",
    "thumb": null,
    "score": 19,
    "views": 27407,
    "crawled_at": "2026-06-10T21:35:37.062078+00:00"
  },
  {
    "id": "710881",
    "site": "ppomppu",
    "title": "(T멤) 맥심 모카골드 190T 20,560원, 백진미채1kg 16,220원, 하겐다즈 파인트 3개 21,710원, 삼다수, 신라면, 사이즈업, 서울우유 (...",
    "url": "https://www.ppomppu.co.kr/zboard/view.php?id=ppomppu&page=1&divpage=113&no=710881",
    "thumb": "https://cdn2.ppomppu.co.kr/zboard/data/_thumb/ppomppu/1/small_710881.jpg?t=20260611",
    "score": 14,
    "views": 10179,
    "crawled_at": "2026-06-10T21:35:37.062078+00:00"
  },
  {
    "id": "1020",
    "site": "ruliweb",
    "title": "[한국PS스토어] 상반기 결산 세일 최대 80% 할인(16)",
    "url": "https://bbs.ruliweb.com/market/board/1020/read/104708?",
    "thumb": null,
    "score": 14,
    "views": 28310,
    "crawled_at": "2026-06-10T21:35:37.062078+00:00"
  },
  {
    "id": "1020",
    "site": "ruliweb",
    "title": "[KFC] 올데이 치킨나이트 치킨 단품 1+1 (6/11)(33)",
    "url": "https://bbs.ruliweb.com/market/board/1020/read/104723?",
    "thumb": null,
    "score": 13,
    "views": 25115,
    "crawled_at": "2026-06-10T21:35:37.062078+00:00"
  },
  {
    "id": "1020",
    "site": "ruliweb",
    "title": "옥션) 터틀비치 리콘 게임패드 39900 / 2500(15)",
    "url": "https://bbs.ruliweb.com/market/board/1020/read/104719?",
    "thumb": null,
    "score": 11,
    "views": 26439,
    "crawled_at": "2026-06-10T21:35:37.062078+00:00"
  },
  {
    "id": "1020",
    "site": "ruliweb",
    "title": "[오늘의집] 하겐다즈 파인트 2+2 28,886원 (무료)",
    "url": "https://bbs.ruliweb.com/market/board/1020/read/104729?",
    "thumb": null,
    "score": 10,
    "views": 6803,
    "crawled_at": "2026-06-10T21:35:37.062078+00:00"
  },
  {
    "id": "1020",
    "site": "ruliweb",
    "title": "[오늘의집] 하겐다즈 파인트 2+2 28,886원 (무료)(8)",
    "url": "https://bbs.ruliweb.com/market/board/1020/read/104729?",
    "thumb": null,
    "score": 10,
    "views": 6825,
    "crawled_at": "2026-06-10T21:35:37.062078+00:00"
  },
  {
    "id": "1020",
    "site": "ruliweb",
    "title": "[맥도날드] 피파 월드컵 리유저블컵 세트 8900원&이달의 해피밀 (6/...",
    "url": "https://bbs.ruliweb.com/market/board/1020/read/104728?",
    "thumb": null,
    "score": 9,
    "views": 10549,
    "crawled_at": "2026-06-10T21:35:37.062078+00:00"
  },
  {
    "id": "1020",
    "site": "ruliweb",
    "title": "[맥도날드] 피파 월드컵 리유저블컵 세트 8900원&이달의 해피밀 (6/...(16)",
    "url": "https://bbs.ruliweb.com/market/board/1020/read/104728?",
    "thumb": null,
    "score": 9,
    "views": 10590,
    "crawled_at": "2026-06-10T21:35:37.062078+00:00"
  },
  {
    "id": "1020",
    "site": "ruliweb",
    "title": "[겜우리] PS5 헤일로 캠페인 이볼브드 한글판 예약 판매 / 69,80...(20)",
    "url": "https://bbs.ruliweb.com/market/board/1020/read/104717?",
    "thumb": null,
    "score": 9,
    "views": 23073,
    "crawled_at": "2026-06-10T21:35:37.062078+00:00"
  },
  {
    "id": "1020",
    "site": "ruliweb",
    "title": "[던킨도너츠] 네이버페이로 12000원 결제시 4800원 할인 외 (6/...",
    "url": "https://bbs.ruliweb.com/market/board/1020/read/104727?",
    "thumb": null,
    "score": 8,
    "views": 3954,
    "crawled_at": "2026-06-10T21:35:37.062078+00:00"
  },
  {
    "id": "1020",
    "site": "ruliweb",
    "title": "[던킨도너츠] 네이버페이로 12000원 결제시 4800원 할인 외 (6/...(2)",
    "url": "https://bbs.ruliweb.com/market/board/1020/read/104727?",
    "thumb": null,
    "score": 8,
    "views": 3964,
    "crawled_at": "2026-06-10T21:35:37.062078+00:00"
  },
  {
    "id": "1020",
    "site": "ruliweb",
    "title": "[에픽게임즈]FC 26 / 6600원 최저가(8)",
    "url": "https://bbs.ruliweb.com/market/board/1020/read/104732?",
    "thumb": null,
    "score": 7,
    "views": 4073,
    "crawled_at": "2026-06-10T21:35:37.062078+00:00"
  },
  {
    "id": "1020",
    "site": "ruliweb",
    "title": "[지마켓] 배홍동막국수 8개+비빔면 8개+장바구니 (11,900원/무료)(17)",
    "url": "https://bbs.ruliweb.com/market/board/1020/read/104716?",
    "thumb": null,
    "score": 7,
    "views": 10303,
    "crawled_at": "2026-06-10T21:35:37.062078+00:00"
  },
  {
    "id": "1020",
    "site": "ruliweb",
    "title": "[롯데온] 피죤 습기제로 제습제 275g 24개 (17,900원/무료)(9)",
    "url": "https://bbs.ruliweb.com/market/board/1020/read/104725?",
    "thumb": null,
    "score": 6,
    "views": 5501,
    "crawled_at": "2026-06-10T21:35:37.062078+00:00"
  },
  {
    "id": "1020",
    "site": "ruliweb",
    "title": "[플레이샵] PS5 인왕 컬렉션 / 22800(무료)(27)",
    "url": "https://bbs.ruliweb.com/market/board/1020/read/104714?",
    "thumb": null,
    "score": 6,
    "views": 11260,
    "crawled_at": "2026-06-10T21:35:37.062078+00:00"
  },
  {
    "id": "1020",
    "site": "ruliweb",
    "title": "[kt콘텐츠페이] 대한민국vs체코 경기 결과에 따라 차등 할인(2)",
    "url": "https://bbs.ruliweb.com/market/board/1020/read/104733?",
    "thumb": null,
    "score": 5,
    "views": 4468,
    "crawled_at": "2026-06-10T21:35:37.062078+00:00"
  },
  {
    "id": "1020",
    "site": "ruliweb",
    "title": "[네이버] 솔라테리아 디럭스에디션(69,800원/유배)(1)",
    "url": "https://bbs.ruliweb.com/market/board/1020/read/104720?",
    "thumb": null,
    "score": 5,
    "views": 11107,
    "crawled_at": "2026-06-10T21:35:37.062078+00:00"
  },
  {
    "id": "1020",
    "site": "ruliweb",
    "title": "[대원샵] 스위치 인생게임 / (44,800 / 2,500)(15)",
    "url": "https://bbs.ruliweb.com/market/board/1020/read/104715?",
    "thumb": null,
    "score": 5,
    "views": 11905,
    "crawled_at": "2026-06-10T21:35:37.062078+00:00"
  },
  {
    "id": "1020",
    "site": "ruliweb",
    "title": "[29cm] 닌텐도 스위치2 2차 예약구매(10)",
    "url": "https://bbs.ruliweb.com/market/board/1020/read/104709?",
    "thumb": null,
    "score": 5,
    "views": 13878,
    "crawled_at": "2026-06-10T21:35:37.062078+00:00"
  },
  {
    "id": "1020",
    "site": "ruliweb",
    "title": "[네이버]삼성전자 갤럭시 버즈4 프로 온누리 환급 (359,000원/무료...(34)",
    "url": "https://bbs.ruliweb.com/market/board/1020/read/104721?",
    "thumb": null,
    "score": 4,
    "views": 22568,
    "crawled_at": "2026-06-10T21:35:37.062078+00:00"
  },
  {
    "id": "710873",
    "site": "ppomppu",
    "title": "BENSIMON 벤시몽 냉감 스판 일자핏 여름슬랙스(18,900원/무료)",
    "url": "https://www.ppomppu.co.kr/zboard/view.php?id=ppomppu&page=1&divpage=113&no=710873",
    "thumb": "https://cdn2.ppomppu.co.kr/zboard/data/_thumb/ppomppu/3/small_710873.jpg?t=20260611",
    "score": 3,
    "views": 8636,
    "crawled_at": "2026-06-10T21:35:37.062078+00:00"
  },
  {
    "id": "710879",
    "site": "ppomppu",
    "title": "하겐다즈 파인트 아이스크림 2+2 골라담기 (30,886원/무배)",
    "url": "https://www.ppomppu.co.kr/zboard/view.php?id=ppomppu&page=1&divpage=113&no=710879",
    "thumb": "https://cdn2.ppomppu.co.kr/zboard/data/_thumb/ppomppu/9/small_710879.jpg?t=20260611",
    "score": 2,
    "views": 2469,
    "crawled_at": "2026-06-10T21:35:37.062078+00:00"
  },
  {
    "id": "1020",
    "site": "ruliweb",
    "title": "[11번가]핫식스 더킹 제로 355ml 24개 외 (티멤버십 16,750...(3)",
    "url": "https://bbs.ruliweb.com/market/board/1020/read/104724?",
    "thumb": null,
    "score": 2,
    "views": 5750,
    "crawled_at": "2026-06-10T21:35:37.062078+00:00"
  },
  {
    "id": "1020",
    "site": "ruliweb",
    "title": "[지마켓]MSI MAG 272URDF800 E16 4K(농.비.스329,...(4)",
    "url": "https://bbs.ruliweb.com/market/board/1020/read/104711?",
    "thumb": null,
    "score": 2,
    "views": 8854,
    "crawled_at": "2026-06-10T21:35:37.062078+00:00"
  },
  {
    "id": "1020",
    "site": "ruliweb",
    "title": "[롯데온] 오리온 나쵸3개+눈을감자3개+뉴룽지3개 (11,330원/무료)(3)",
    "url": "https://bbs.ruliweb.com/market/board/1020/read/104707?",
    "thumb": null,
    "score": 2,
    "views": 6581,
    "crawled_at": "2026-06-10T21:35:37.062078+00:00"
  },
  {
    "id": "710890",
    "site": "ppomppu",
    "title": "있나요 리얼 그릭요거트 스타터 10포 x 2박스 (11,790원/무료)",
    "url": "https://www.ppomppu.co.kr/zboard/view.php?id=ppomppu&page=1&divpage=113&no=710890",
    "thumb": "https://cdn2.ppomppu.co.kr/zboard/data/_thumb/ppomppu/0/small_710890.jpg?t=20260611",
    "score": 1,
    "views": 2050,
    "crawled_at": "2026-06-10T21:35:37.062078+00:00"
  },
  {
    "id": "49071",
    "site": "ppomppu",
    "title": "머거본 치즈스낵&꿀땅콩 400g 2봉 5,900원 무배",
    "url": "https://www.ppomppu.co.kr/zboard/zboard/view.php?id=social&no=49071",
    "thumb": "https://cdn2.ppomppu.co.kr/zboard/data3/2026/0610/20260610222819_Ez3yTPxHlX.jpg",
    "score": 1,
    "views": 1165,
    "crawled_at": "2026-06-10T21:35:37.062078+00:00"
  },
  {
    "id": "1020",
    "site": "ruliweb",
    "title": "[스팀] P의 거짓 50% 할인 / 32,400원(7)",
    "url": "https://bbs.ruliweb.com/market/board/1020/read/104710?",
    "thumb": null,
    "score": 1,
    "views": 8039,
    "crawled_at": "2026-06-10T21:35:37.062078+00:00"
  },
  {
    "id": "710897",
    "site": "ppomppu",
    "title": "FC 26 Standard Edition (6600원/무료)",
    "url": "https://www.ppomppu.co.kr/zboard/view.php?id=ppomppu&page=1&divpage=113&no=710897",
    "thumb": "https://cdn2.ppomppu.co.kr/zboard/data/_thumb/ppomppu/7/small_710897.jpg?t=20260611",
    "score": 0,
    "views": 1905,
    "crawled_at": "2026-06-10T21:35:37.062078+00:00"
  },
  {
    "id": "710896",
    "site": "ppomppu",
    "title": "삼성 Neo QLED AI TV 163cm(65인치) KQ65QNH70AFXKR (삼카 1,645,100원/무료)",
    "url": "https://www.ppomppu.co.kr/zboard/view.php?id=ppomppu&page=1&divpage=113&no=710896",
    "thumb": "https://cdn2.ppomppu.co.kr/zboard/data/_thumb/ppomppu/6/small_710896.jpg?t=20260611",
    "score": 0,
    "views": 2758,
    "crawled_at": "2026-06-10T21:35:37.062078+00:00"
  },
  {
    "id": "710895",
    "site": "ppomppu",
    "title": "락토핏 골드 7통 350일분+30포증정외(49,040원/무료)",
    "url": "https://www.ppomppu.co.kr/zboard/view.php?id=ppomppu&page=1&divpage=113&no=710895",
    "thumb": "https://cdn2.ppomppu.co.kr/zboard/data/_thumb/ppomppu/5/small_710895.jpg?t=20260611",
    "score": 0,
    "views": 2073,
    "crawled_at": "2026-06-10T21:35:37.062078+00:00"
  },
  {
    "id": "710894",
    "site": "ppomppu",
    "title": "얼갈이김치 2kg + 열무김치 2kg 총 4kg (11,700원/무배)",
    "url": "https://www.ppomppu.co.kr/zboard/view.php?id=ppomppu&page=1&divpage=113&no=710894",
    "thumb": "https://cdn2.ppomppu.co.kr/zboard/data/_thumb/ppomppu/4/small_710894.jpg?t=20260611",
    "score": 0,
    "views": 7555,
    "crawled_at": "2026-06-10T21:35:37.062078+00:00"
  },
  {
    "id": "710893",
    "site": "ppomppu",
    "title": "삼성 스마트모니터 M7 S32FM701 32인치 UHD 4K + 이동식 스탠드(농카 495,050원/무료)",
    "url": "https://www.ppomppu.co.kr/zboard/view.php?id=ppomppu&page=1&divpage=113&no=710893",
    "thumb": "https://cdn2.ppomppu.co.kr/zboard/data/_thumb/ppomppu/3/small_710893.jpg?t=20260611",
    "score": 0,
    "views": 3889,
    "crawled_at": "2026-06-10T21:35:37.062078+00:00"
  },
  {
    "id": "710892",
    "site": "ppomppu",
    "title": "여수 돌산갓김치 2kg (9,900원/무료)",
    "url": "https://www.ppomppu.co.kr/zboard/view.php?id=ppomppu&page=1&divpage=113&no=710892",
    "thumb": "https://cdn2.ppomppu.co.kr/zboard/data/_thumb/ppomppu/2/small_710892.jpg?t=20260611",
    "score": 0,
    "views": 1807,
    "crawled_at": "2026-06-10T21:35:37.062078+00:00"
  },
  {
    "id": "710891",
    "site": "ppomppu",
    "title": "국내산 생물 오징어 1kg 당일 조업 (16,900원/무료배송)",
    "url": "https://www.ppomppu.co.kr/zboard/view.php?id=ppomppu&page=1&divpage=113&no=710891",
    "thumb": "https://cdn2.ppomppu.co.kr/zboard/data/_thumb/ppomppu/1/small_710891.jpg?t=20260611",
    "score": 0,
    "views": 2712,
    "crawled_at": "2026-06-10T21:35:37.062078+00:00"
  },
  {
    "id": "710889",
    "site": "ppomppu",
    "title": "상도 순살치킨 가라아게 1kg 2팩 (20,700원/무배)",
    "url": "https://www.ppomppu.co.kr/zboard/view.php?id=ppomppu&page=1&divpage=113&no=710889",
    "thumb": "https://cdn2.ppomppu.co.kr/zboard/data/_thumb/ppomppu/9/small_710889.jpg?t=20260611",
    "score": 0,
    "views": 2392,
    "crawled_at": "2026-06-10T21:35:37.062078+00:00"
  },
  {
    "id": "710888",
    "site": "ppomppu",
    "title": "진우린 푸짐한 프리미엄 갈비탕 1kg 4팩 (39,840원/무료)",
    "url": "https://www.ppomppu.co.kr/zboard/view.php?id=ppomppu&page=1&divpage=113&no=710888",
    "thumb": "https://cdn2.ppomppu.co.kr/zboard/data/_thumb/ppomppu/8/small_710888.jpg?t=20260611",
    "score": 0,
    "views": 1932,
    "crawled_at": "2026-06-10T21:35:37.062078+00:00"
  },
  {
    "id": "710887",
    "site": "ppomppu",
    "title": "와이드형 대용량 제습제 24개 (14,900원/무료)",
    "url": "https://www.ppomppu.co.kr/zboard/view.php?id=ppomppu&page=1&divpage=113&no=710887",
    "thumb": "https://cdn2.ppomppu.co.kr/zboard/data/_thumb/ppomppu/7/small_710887.jpg?t=20260611",
    "score": 0,
    "views": 2415,
    "crawled_at": "2026-06-10T21:35:37.062078+00:00"
  },
  {
    "id": "710886",
    "site": "ppomppu",
    "title": "직화 무뼈 불닭발 170g 4팩 (18,270원/무료)",
    "url": "https://www.ppomppu.co.kr/zboard/view.php?id=ppomppu&page=1&divpage=113&no=710886",
    "thumb": "https://cdn2.ppomppu.co.kr/zboard/data/_thumb/ppomppu/6/small_710886.jpg?t=20260611",
    "score": 0,
    "views": 2211,
    "crawled_at": "2026-06-10T21:35:37.062078+00:00"
  },
  {
    "id": "710885",
    "site": "ppomppu",
    "title": "국내산 별미 통 오이지 1.5kg (11,390원/무배)",
    "url": "https://www.ppomppu.co.kr/zboard/view.php?id=ppomppu&page=1&divpage=113&no=710885",
    "thumb": "https://cdn2.ppomppu.co.kr/zboard/data/_thumb/ppomppu/5/small_710885.jpg?t=20260611",
    "score": 0,
    "views": 2047,
    "crawled_at": "2026-06-10T21:35:37.062078+00:00"
  },
  {
    "id": "710884",
    "site": "ppomppu",
    "title": "일상미당 영양 약밥 15개입 (개별포장 1kg) (16,900원/무배)",
    "url": "https://www.ppomppu.co.kr/zboard/view.php?id=ppomppu&page=1&divpage=113&no=710884",
    "thumb": "https://cdn2.ppomppu.co.kr/zboard/data/_thumb/ppomppu/4/small_710884.jpg?t=20260611",
    "score": 0,
    "views": 1859,
    "crawled_at": "2026-06-10T21:35:37.062078+00:00"
  },
  {
    "id": "710883",
    "site": "ppomppu",
    "title": "네파 남여공용 에센셜 2L 미드 덕다운자켓 (79,730원/무료배송)",
    "url": "https://www.ppomppu.co.kr/zboard/view.php?id=ppomppu&page=1&divpage=113&no=710883",
    "thumb": "https://cdn2.ppomppu.co.kr/zboard/data/_thumb/ppomppu/3/small_710883.jpg?t=20260611",
    "score": 0,
    "views": 12075,
    "crawled_at": "2026-06-10T21:35:37.062078+00:00"
  },
  {
    "id": "710882",
    "site": "ppomppu",
    "title": "프레시웰 500ml X 80개(13,890원/무료)",
    "url": "https://www.ppomppu.co.kr/zboard/view.php?id=ppomppu&page=1&divpage=113&no=710882",
    "thumb": "https://cdn2.ppomppu.co.kr/zboard/data/_thumb/ppomppu/2/small_710882.jpg?t=20260611",
    "score": 0,
    "views": 2115,
    "crawled_at": "2026-06-10T21:35:37.062078+00:00"
  },
  {
    "id": "710880",
    "site": "ppomppu",
    "title": "뱀부 소재 밴딩 반바지 (21,100원/무료)",
    "url": "https://www.ppomppu.co.kr/zboard/view.php?id=ppomppu&page=1&divpage=113&no=710880",
    "thumb": "https://cdn2.ppomppu.co.kr/zboard/data/_thumb/ppomppu/0/small_710880.jpg?t=20260611",
    "score": 0,
    "views": 2831,
    "crawled_at": "2026-06-10T21:35:37.062078+00:00"
  },
  {
    "id": "710878",
    "site": "ppomppu",
    "title": "에스란 3개월+4주분/150g+60g (65,900원/무료)",
    "url": "https://www.ppomppu.co.kr/zboard/view.php?id=ppomppu&page=1&divpage=113&no=710878",
    "thumb": "https://cdn2.ppomppu.co.kr/zboard/data/_thumb/ppomppu/8/small_710878.jpg?t=20260611",
    "score": 0,
    "views": 1494,
    "crawled_at": "2026-06-10T21:35:37.062078+00:00"
  },
  {
    "id": "302671",
    "site": "ppomppu",
    "title": "[토스쇼핑] 팬택 25W 1포트 C타입 초고속충전기 / 기꼬만 혼쯔유 코이다시 500ml 2개 /순살 양념 목살구이 600g 3개",
    "url": "https://www.ppomppu.co.kr/zboard/zboard/view.php?id=pmarket&&no=302671",
    "thumb": "https://cdn2.ppomppu.co.kr/zboard/data/_thumb/pmarket/1/small_302671.jpg",
    "score": 0,
    "views": 2944,
    "crawled_at": "2026-06-10T21:35:37.062078+00:00"
  },
  {
    "id": "302689",
    "site": "ppomppu",
    "title": "[토스쇼핑] 애슐리 냉동 트리플 베리믹스 1kg 3개 / HBAF 팝콘 맛보기 세트 8종",
    "url": "https://www.ppomppu.co.kr/zboard/zboard/view.php?id=pmarket&&no=302689",
    "thumb": "https://cdn2.ppomppu.co.kr/zboard/data/_thumb/pmarket/9/small_302689.jpg",
    "score": 0,
    "views": 540,
    "crawled_at": "2026-06-10T21:35:37.062078+00:00"
  },
  {
    "id": "302677",
    "site": "ppomppu",
    "title": "[삼성전자모음] 갤럭시 탭 / 스마트 모니터  / 세탁건조기 / 휴대폰 / 버즈 / TV",
    "url": "https://www.ppomppu.co.kr/zboard/zboard/view.php?id=pmarket&&no=302677",
    "thumb": "https://cdn2.ppomppu.co.kr/zboard/data/_thumb/pmarket/7/small_302677.jpg",
    "score": 0,
    "views": 2587,
    "crawled_at": "2026-06-10T21:35:37.062078+00:00"
  },
  {
    "id": "49070",
    "site": "ppomppu",
    "title": "맥도날드 FIFA 월드컵 세트 출시",
    "url": "https://www.ppomppu.co.kr/zboard/zboard/view.php?id=social&no=49070",
    "thumb": "https://cdn2.ppomppu.co.kr/zboard/data3/2026/0610/20260610200228_NyeAAyfnF9.jpg",
    "score": 0,
    "views": 9314,
    "crawled_at": "2026-06-10T21:35:37.062078+00:00"
  },
  {
    "id": "49068",
    "site": "ppomppu",
    "title": "메탈랙 선반 부품 검색중인데- 쿠팡은 계속 에러나고 연결이 안되는거 저만 그런가요?",
    "url": "https://www.ppomppu.co.kr/zboard/zboard/view.php?id=social&no=49068",
    "thumb": "https://cdn2.ppomppu.co.kr/zboard/",
    "score": 0,
    "views": 1045,
    "crawled_at": "2026-06-10T21:35:37.062078+00:00"
  },
  {
    "id": "1020",
    "site": "ruliweb",
    "title": "[네이버] 깨끗한나라 3겹 순수프리미엄 롤화장지 27m X 30롤 1+1...(7)",
    "url": "https://bbs.ruliweb.com/market/board/1020/read/104713?",
    "thumb": null,
    "score": 0,
    "views": 7343,
    "crawled_at": "2026-06-10T21:35:37.062078+00:00"
  }
]